acw_sc_v2_py/__init__.py
acw_sc_v2_py/acw_sc__v2.py
acw_sc_v2_py-0.0.6.dist-info/METADATA
acw_sc_v2_py-0.0.6.dist-info/WHEEL
acw_sc_v2_py-0.0.6.dist-info/top_level.txt
acw_sc_v2_py-0.0.6.dist-info/RECORD
