Metadata-Version: 2.4
Name: acw-sc-v2-py
Version: 0.0.6
Summary: Add your description here
Requires-Python: >=3.12
Requires-Dist: requests>=2.32.3
